based/__init__.py
based/cache.py
based/chat_manager.py
based/cli.py
based/config.py
based/prompts.json
based_cli-0.0.7.dist-info/METADATA
based_cli-0.0.7.dist-info/WHEEL
based_cli-0.0.7.dist-info/entry_points.txt
based_cli-0.0.7.dist-info/licenses/LICENSE
based_cli-0.0.7.dist-info/RECORD
