Metadata-Version: 2.4
Name: based-cli
Version: 0.0.7
Summary: A powerful CLI tool for interacting with various AI models
Project-URL: Homepage, https://github.com/yourusername/based
Project-URL: Documentation, https://github.com/yourusername/based#readme
Project-URL: Repository, https://github.com/yourusername/based.git
Project-URL: Issues, https://github.com/yourusername/based/issues
Author-email: Your Name <your.email@example.com>
License-Expression: MIT
License-File: LICENSE
Keywords: ai,anthropic,chatbot,cli,groq,huggingface,mistral,openai
Classifier: Development Status :: 4 - Beta
Classifier: Environment :: Console
Classifier: Intended Audience :: Developers
Classifier: License :: OSI Approved :: MIT License
Classifier: Programming Language :: Python :: 3
Classifier: Programming Language :: Python :: 3.9
Classifier: Programming Language :: Python :: 3.10
Classifier: Programming Language :: Python :: 3.11
Classifier: Programming Language :: Python :: 3.12
Classifier: Topic :: Software Development :: Libraries :: Python Modules
Classifier: Topic :: Software Development :: User Interfaces
Requires-Python: >=3.9
Requires-Dist: anthropic>=0.30.0
Requires-Dist: groq>=0.4.2
Requires-Dist: huggingface-hub>=0.26.5
Requires-Dist: langchain-anthropic>=0.2.0
Requires-Dist: langchain-core>=0.3.29
Requires-Dist: langchain-groq>=0.2.3
Requires-Dist: langchain-huggingface>=0.1.2
Requires-Dist: langchain-mistralai>=0.2.4
Requires-Dist: langchain-openai>=0.3.0
Requires-Dist: mistralai>=0.0.12
Requires-Dist: openai<2.0.0,>=1.58.1
Requires-Dist: python-dotenv>=1.0.1
Requires-Dist: questionary>=2.1.0
Requires-Dist: rich>=13.9.4
Requires-Dist: typer>=0.15.1
